gdrive/__init__.py
gdrive/__main__.py
gdrive/gdrive.py
gdrive_python-1.0.8.dist-info/METADATA
gdrive_python-1.0.8.dist-info/WHEEL
gdrive_python-1.0.8.dist-info/top_level.txt
gdrive_python-1.0.8.dist-info/RECORD
